cimport/__init__.py
cimport/c/__init__.py
cimport/c/compile.py
cimport/c/program.py
cimport/javascript/__init__.py
cimport/rust/__init__.py
cimport/rust/compile.py
cimport/utils/cache_file/__init__.py
cimport/utils/command/base.py
cimport/utils/command/linux.py
cimport/utils/command/window.py
cimport-0.3.1rc0.dist-info/LICENSE
cimport-0.3.1rc0.dist-info/METADATA
cimport-0.3.1rc0.dist-info/WHEEL
cimport-0.3.1rc0.dist-info/top_level.txt
cimport-0.3.1rc0.dist-info/RECORD
