Metadata-Version: 2.1
Name: cimport
Version: 0.3.1rc0
Summary: a Foreign language Import library for python
Author-email: Fakesum <worldanvilbild+github@gmail.com>
Project-URL: Homepage, https://github.com/Fakesum/cimport
Project-URL: Bug Tracker, https://github.com/Fakesum/cimport/issues
Classifier: Programming Language :: Python :: 3
Classifier: License :: OSI Approved :: MIT License
Classifier: Operating System :: OS Independent
Requires-Python: >=3.9
License-File: LICENSE
